myADconvert/__init__.py
myADconvert/myADconvert.py
myADconvert-3.0.0.dist-info/METADATA
myADconvert-3.0.0.dist-info/WHEEL
myADconvert-3.0.0.dist-info/top_level.txt
myADconvert-3.0.0.dist-info/RECORD
